neatadjacency/__init__.py
neatadjacency/adjacency.py
neatadjacency/edge.py
neatadjacency/shape.py
neatadjacency/vertex.py
neatadjacency-1.0.0.dist-info/LICENSE
neatadjacency-1.0.0.dist-info/METADATA
neatadjacency-1.0.0.dist-info/WHEEL
neatadjacency-1.0.0.dist-info/top_level.txt
neatadjacency-1.0.0.dist-info/RECORD
