Metadata-Version: 2.1
Name: neatadjacency
Version: 1.0.0
Summary: An adjacency list implementation.
Home-page: https://gitlab.com/landreville/neatadjacency
Author: Landreville
License: UNKNOWN
Platform: UNKNOWN
Classifier: Programming Language :: Python
Classifier: Programming Language :: Python :: 3
Classifier: Programming Language :: Python :: Implementation :: PyPy
Classifier: License :: OSI Approved :: GNU Affero General Public License v3
Requires-Dist: sortedcontainers
